README.md
chaingree_nester.py
setup.py
test.py
chaingree_nester.egg-info/PKG-INFO
chaingree_nester.egg-info/SOURCES.txt
chaingree_nester.egg-info/dependency_links.txt
chaingree_nester.egg-info/top_level.txt