Metadata-Version: 1.0
Name: chaingree-nester
Version: 1.0.0
Summary: Python pro upload test
Home-page: https://user.qzone.qq.com/254756875/infocenter
Author: chaingree
Author-email: 254756875@qq.com
License: UNKNOWN
Platform: UNKNOWN
